memory_chatbot/__init__.py
memory_chatbot/cli/__init__.py
memory_chatbot/cli/commands.py
memory_chatbot/config/__init__.py
memory_chatbot/config/loader.py
memory_chatbot/config/settings.py
memory_chatbot/core/__init__.py
memory_chatbot/core/chat_controller.py
memory_chatbot/core/domain_detector.py
memory_chatbot/core/global_memory.py
memory_chatbot/core/legacy_memory_adapter.py
memory_chatbot/core/mem0_memory_adapter.py
memory_chatbot/core/memory_adapter.py
memory_chatbot/core/memory_adapter_factory.py
memory_chatbot/core/memory_extractor.py
memory_chatbot/core/session_manager.py
memory_chatbot/core/workspace_memory.py
memory_chatbot/main.py
memory_chatbot/providers/__init__.py
memory_chatbot/providers/base.py
memory_chatbot/providers/claude_provider.py
memory_chatbot/providers/mem0_provider.py
memory_chatbot/providers/openai_provider.py
memory_chatbot/utils/__init__.py
memory_chatbot/utils/crypto.py
karma_mvp-0.1.3.dist-info/METADATA
karma_mvp-0.1.3.dist-info/WHEEL
karma_mvp-0.1.3.dist-info/entry_points.txt
karma_mvp-0.1.3.dist-info/RECORD
