Metadata-Version: 2.3
Name: karma-mvp
Version: 0.1.3
Summary: Multi-domain AI assistant with three-layer memory architecture (Global-Workspace-Session) for personalized, context-aware conversations
Keywords: ai,chatbot,memory,assistant,cli,multi-domain,personalization
Author: Karma AI Team
Author-email: team@karma-ai.com
Requires-Python: >=3.8,<4.0
Classifier: Development Status :: 4 - Beta
Classifier: Environment :: Console
Classifier: Intended Audience :: Developers
Classifier: Intended Audience :: End Users/Desktop
Classifier: License :: OSI Approved :: MIT License
Classifier: Operating System :: OS Independent
Classifier: Programming Language :: Python :: 3
Classifier: Programming Language :: Python :: 3.8
Classifier: Programming Language :: Python :: 3.9
Classifier: Programming Language :: Python :: 3.10
Classifier: Programming Language :: Python :: 3.11
Classifier: Programming Language :: Python :: 3.12
Classifier: Programming Language :: Python :: 3.13
Classifier: Topic :: Communications :: Chat
Classifier: Topic :: Office/Business
Classifier: Topic :: Scientific/Engineering :: Artificial Intelligence
Provides-Extra: all
Provides-Extra: mem0
Requires-Dist: aiofiles (>=23.0,<24.0)
Requires-Dist: click (>=8.0,<9.0)
Requires-Dist: cryptography (>=41.0,<42.0)
Requires-Dist: httpx (>=0.27,<0.28)
Requires-Dist: jinja2 (>=3.1,<4.0)
Requires-Dist: mem0ai (>=0.1.0,<0.2.0) ; extra == "mem0" or extra == "all"
Requires-Dist: pyyaml (>=6.0,<7.0)
Requires-Dist: rich (>=13.0,<14.0)
Project-URL: Documentation, https://github.com/karma-ai/karma-mvp/blob/main/docs/
Project-URL: Homepage, https://github.com/karma-ai/karma-mvp
Project-URL: Repository, https://github.com/karma-ai/karma-mvp
